{
  "kind": "collectionType",
  "collectionName": "module_progresses",
  "info": {
    "singularName": "module-progress",
    "pluralName": "module-progresses",
    "displayName": "module-progress"
  },
  "options": {
    "draftAndPublish": false
  },
  "pluginOptions": {},
  "attributes": {
    "module": {
      "type": "relation",
      "relation": "manyToOne",
      "target": "api::module.module"
    },
    "users_permissions_user": {
      "type": "relation",
      "relation": "manyToOne",
      "target": "plugin::users-permissions.user"
    },
    "videoWatched": {
      "type": "boolean",
      "default": false
    },
    "quizCompleted": {
      "type": "boolean",
      "default": false
    },
    "completed": {
      "type": "boolean",
      "default": false
    }
  }
}
